setup.py
ads_bd/__init__.py
ads_bd/main.py
ads_bd.egg-info/PKG-INFO
ads_bd.egg-info/SOURCES.txt
ads_bd.egg-info/dependency_links.txt
ads_bd.egg-info/not-zip-safe
ads_bd.egg-info/requires.txt
ads_bd.egg-info/top_level.txt