Metadata-Version: 1.0
Name: ads-bd
Version: 0.1
Summary: ads big data
Home-page: https://github.com/li-lu/bd/tree/master/python
Author: li-lu
Author-email: li_lu2000@hotmail.com
License: MIT
Platform: UNKNOWN
